sshcmd/__init__.py
sshcmd/sshcmd.py
sshcmd-0.3.dist-info/METADATA
sshcmd-0.3.dist-info/WHEEL
sshcmd-0.3.dist-info/top_level.txt
sshcmd-0.3.dist-info/RECORD
